README.md
setup.py
mockserver/__init__.py
mockserver/api_client.py
mockserver/configuration.py
mockserver/rest.py
mockserver/api/__init__.py
mockserver/api/control_api.py
mockserver/api/expectation_api.py
mockserver/api/verify_api.py
mockserver/models/__init__.py
mockserver/models/body.py
mockserver/models/body_with_content_type.py
mockserver/models/connection_options.py
mockserver/models/delay.py
mockserver/models/expectation.py
mockserver/models/expectations.py
mockserver/models/http_class_callback.py
mockserver/models/http_error.py
mockserver/models/http_forward.py
mockserver/models/http_object_callback.py
mockserver/models/http_override_forwarded_request.py
mockserver/models/http_request.py
mockserver/models/http_response.py
mockserver/models/http_template.py
mockserver/models/key_to_multi_value.py
mockserver/models/key_to_value.py
mockserver/models/ports.py
mockserver/models/time_to_live.py
mockserver/models/times.py
mockserver/models/verification.py
mockserver/models/verification_sequence.py
mockserver/models/verification_times.py
mp_mockserver_client.egg-info/PKG-INFO
mp_mockserver_client.egg-info/SOURCES.txt
mp_mockserver_client.egg-info/dependency_links.txt
mp_mockserver_client.egg-info/requires.txt
mp_mockserver_client.egg-info/top_level.txt
test/__init__.py
test/test_body.py
test/test_body_with_content_type.py
test/test_connection_options.py
test/test_control_api.py
test/test_delay.py
test/test_expectation.py
test/test_expectation_api.py
test/test_expectations.py
test/test_http_class_callback.py
test/test_http_error.py
test/test_http_forward.py
test/test_http_object_callback.py
test/test_http_override_forwarded_request.py
test/test_http_request.py
test/test_http_response.py
test/test_http_template.py
test/test_key_to_multi_value.py
test/test_key_to_value.py
test/test_ports.py
test/test_time_to_live.py
test/test_times.py
test/test_verification.py
test/test_verification_sequence.py
test/test_verification_times.py
test/test_verify_api.py