Metadata-Version: 1.0
Name: mp-mockserver-client
Version: 5.3.0
Summary: Mock Server API
Home-page: https://mock-server.com/
Author: UNKNOWN
Author-email: mptnt1988@gmail.com
License: UNKNOWN
Keywords: Mock Server API,Mock Server,HTTP Mock,Proxy
Platform: UNKNOWN
